urb/__init__.py
urb/__main__.py
urb/prints.py
urb/wrappers/__init__.py
urb/wrappers/google.py
urb/wrappers/quote.py
urb/wrappers/spell_check.py
urb/wrappers/urban.py
urb/wrappers/wotd.py
urb-1.2.3.dist-info/LICENSE
urb-1.2.3.dist-info/METADATA
urb-1.2.3.dist-info/WHEEL
urb-1.2.3.dist-info/entry_points.txt
urb-1.2.3.dist-info/top_level.txt
urb-1.2.3.dist-info/RECORD
